transaction_decoder/__init__.py
transaction_decoder/transaction_decoder.py
transaction_decoder/transaction_decoder_test.py
multiversx_sdk_transaction_decoder-0.4.0.dist-info/METADATA
multiversx_sdk_transaction_decoder-0.4.0.dist-info/WHEEL
multiversx_sdk_transaction_decoder-0.4.0.dist-info/licenses/LICENSE
multiversx_sdk_transaction_decoder-0.4.0.dist-info/RECORD
