Metadata-Version: 2.3
Name: multiversx-sdk-transaction-decoder
Version: 0.4.0
Summary: Deprecated. Instead, use multiversx-sdk.
Project-URL: Homepage, https://github.com/multiversx/mx-sdk-py-transaction-decoder
Author: MultiversX
License-Expression: MIT
License-File: LICENSE
Classifier: Development Status :: 7 - Inactive
Classifier: License :: OSI Approved :: MIT License
Classifier: Operating System :: OS Independent
Classifier: Programming Language :: Python :: 3
Requires-Python: >=3.8
Requires-Dist: multiversx-sdk-core<0.8.0,>=0.7.0
